skelethon/__init__.py
skelethon/__main__.py
skelethon/version.py
skelethon-0.0.1.dev1.dist-info/DESCRIPTION.rst
skelethon-0.0.1.dev1.dist-info/METADATA
skelethon-0.0.1.dev1.dist-info/RECORD
skelethon-0.0.1.dev1.dist-info/WHEEL
skelethon-0.0.1.dev1.dist-info/metadata.json
skelethon-0.0.1.dev1.dist-info/top_level.txt
