Metadata-Version: 2.0
Name: skelethon
Version: 0.0.1.dev1
Summary: Make a SKELEton for pyTHON projects :)
Home-page: https://www.github.com/mplanchard/skelethon
Author: Matthew Planchard
Author-email: msplanchard@gmail.com
License: UNKNOWN
Keywords: python,setup,project,packaging,versioning,skeleton
Platform: UNKNOWN
Classifier: Development Status :: 1 - Planning
Classifier: Intended Audience :: Developers
Classifier: License :: OSI Approved :: MIT License
Classifier: Natural Language :: English
Classifier: Operating System :: POSIX :: Linux
Classifier: Programming Language :: Python
Requires-Dist: click
Requires-Dist: jinja2
